README.md
setup.py
crimereports/__init__.py
crimereports.egg-info/PKG-INFO
crimereports.egg-info/SOURCES.txt
crimereports.egg-info/dependency_links.txt
crimereports.egg-info/requires.txt
crimereports.egg-info/top_level.txt