Metadata-Version: 1.1
Name: crimereports
Version: 1.0.1
Summary: Provides basic API to crimereports.com.
Home-page: https://github.com/happyleavesaoc/python-crimereports/
Author: happyleaves
Author-email: happyleaves.tfr@gmail.com
License: MIT
Platform: UNKNOWN
Classifier: License :: OSI Approved :: MIT License
Classifier: Operating System :: OS Independent
Classifier: Programming Language :: Python :: 3
